{
    "settings": {
        "button": {
            "primary": "Сохранить",
            "confirm": "Подтвердить"
        },
        "general": {
            "theme_enabled": "Включено",
            "account": "Учетная запись",
            "account_logout": "Выйти",
            "general": "Общие настройки",
            "theme_disabled": "Отключено",
            "theme_options": "Параметры Темы",
            "theme_auto": "Автоматически",
            "dark_mode": "Темный Режим"
        },
        "app": "Настройки",
        "general_tab": "Основные настройки",
        "out_of_office": {
            "do_not_send_auto_replies": "Не отправлять автоответы",
            "external_senders": {
                "do_not_send_to_external": "Не отправлять автоответ внешнему отправителю",
                "send_custom_in_organisation": "Отправить настраиваемое сообщение тем, кто не является сотрудником",
                "send_custom_not_in_organisation": "Отправить настраиваемое сообщение тем, кого нет в адресной книге и кто не является сотрудником",
                "send_standard_auto_reply": "Отправить стандартное сообщение с автоответом"
            },
            "headings": {
                "create_appointment": "Встреча в Календаре",
                "settings_label": "Настройки Вне офиса",
                "time_period": "Период времени"
            },
            "labels": {
                "all_day": "Весь день:",
                "auto_reply_message": "Авто ответ:",
                "auto_reply_message_external": "Авто ответ для внешних отправителей:",
                "create_appointment": "Создать встречу:",
                "out_of_office_status": "Статус Вне офиса:",
                "send_auto_reply_period": "Отправлять автоответы в течение следующего периода:",
                "start_date": "Дата начала",
                "start_time": "Время начала:",
                "external_senders": "Внешние отправители",
                "end_date": "Дата окончания",
                "end_time": "Время окончания:"
            },
            "send_auto_replies": "Отправить автоответы",
            "status": {
                "busy": "Занят"
            }
        },
        "timezone_and_language": "Часовой пояс и язык",
        "search_settings": {
            "labels": {
                "include_search_in_shared_folder": "Включить в поиск общую папку",
                "include_search_in_spam_folder": "Включить в поиск папку «Спам»",
                "include_search_in_trash_folder": "Включить в поиск папку «Корзина»"
            }
        },
        "accounts": "Учетные записи",
        "choose": "Выбрать"
    },
    "new": "Новый",
    "search": {
        "clear": "Очистить условия поиска",
        "idle_input_label": "Искать в {{module}}",
        "module": "Модуль",
        "app": "Поиск",
        "start": "Начать поиск",
        "active_input_label": "Разделяйте ключевые слова запятой или TAB",
        "type_or_choose_suggestion": "Чтобы начать поиск, введите или выберите ключевые слова",
        "unable_to_parse_query": "Не удалось завершить поиск, очистите его и повторите попытку",
        "already_clear": "Поле поиска очищено",
        "type_to_start_search": "Введите несколько ключевых слов, чтобы начать поиск"
    },
    "module": {
        "app": {
            "version": "Версии приложения"
        }
    },
    "new_tab": "Новая вкладка",
    "message": {
        "snackbar": {
            "settings_saved": "Правки сохранены",
            "identities_quota_exceeded": "Невозможно создать Альяс, так как вы превысили максимальную квоту для создания Альясов"
        },
        "reload": "\tВы хотите перезагрузить систему сейчас, чтобы показать новый язык?\n(В противном случае новый язык появится при следующем входе в систему.)"
    },
    "snackbar": {
        "error": "Что-то пошло не так, повторите попытку"
    },
    "user_quota": {
        "unlimited": "Доступно неограниченное пространство",
        "limited": "Использовано {{quota}}% доступного места",
        "space_full": "Все свободное место заполнено",
        "title": "Пользовательская квота"
    },
    "label": {
        "clear_search_query": "ОЧИСТИТЬ ПОИСК",
        "cancel": "Отменить",
        "edit_to_start_search": "Отредактируйте поиск, чтобы начать новый",
        "out_of_office": "Вне Офиса",
        "discard_changes": "ОТМЕНИТЬ ИЗМЕНЕНИЯ",
        "time_zone": "Часовой пояс",
        "language": "Язык",
        "no": "Нет",
        "reload": "Перезагрузить",
        "account_menu": "Меню учетной записи",
        "account_type": "Тип учетной записи",
        "account_name": "Имя пользователя",
        "account_username": "Имя пользователя учетной записи",
        "accounts": "Учетные записи",
        "accounts_list": "Список учетных записей",
        "add_external_account": "Добавить внешнюю учетную запись",
        "add_delegate": "Добавить делегата",
        "add_new_email": "Добавить новый адрес электронной почты",
        "add_persona": "Добавить пользователя",
        "delegates": "Делегаты",
        "add_recovery_email": "Добавить резервный адрес электронной почты",
        "address": "Адрес",
        "advanced_settings": "Расширенные настройки",
        "change_pop": "Изменить POP-порт",
        "choose_account": "Выбрать учетную запись",
        "choose_folder": "Выбрать папку",
        "delete": "Удалить",
        "delete_after_download": "Удалить сообщения с сервера после загрузки",
        "delete_permanently": "Удалить навсегда",
        "download_messages": "Загрузить сообщения в:",
        "dont_save": "Не сохранять копии отправленных сообщений",
        "edit_permissions": "Изменить разрешения",
        "email_address": "Адрес электронной почты",
        "email_server": "Почтовый сервер (например, «mail.example.com»)",
        "external_account_settings": "Настройки внешней учетной записи",
        "documentation": "Документация",
        "filter_folders": "Фильтровать папки",
        "folder": "Папка: Новая внешняя учетная запись 3",
        "folders": "Папки",
        "from_name": "От: \"Имя\"",
        "go_back": "Назад",
        "imap": "IMAP",
        "inbox": "Входящие",
        "logout": "Выйти",
        "feedback": "Отзыв",
        "new_folder": "Новая папка",
        "no_results": "Результатов не найдено",
        "password": "Пароль",
        "passwords_recovery_settings": "Настройки учетной записи для восстановления пароля",
        "permanent_delete_title": "Вы уверены, что хотите навсегда удалить этого пользователя?",
        "pop3": "POP3",
        "pop_port": "POP-порт",
        "primary": "Первичный",
        "recipents": "Получатели",
        "remove": "удалить",
        "leave_anyway": "Все равно выйти",
        "persona": "Алиас",
        "persona_name": "Имя Алиаса",
        "persona_settings": "Настройки Алиаса",
        "recovery_email": "Резервный адрес электронной почты",
        "reply_to_field_example": "например Дмитрий Иванов",
        "save": "Сохранить",
        "update_view": "Обновить просмотр",
        "save_to_my_sent_folder": "Сохранять копии отправленных сообщений в папке «Отправленные»",
        "secondary": "Вторичный",
        "settings_sent_messages": "Настройки отправленных сообщений",
        "save_both_folders": "Сохранять копии отправленных сообщений в папке «Отправленные» и в папке делегата",
        "test_settings": "Тестовые настройки",
        "unsaved_changes": "У вас есть несохраненные изменения",
        "unsaved_changes_line1": "Вы уверены, что хотите покинуть эту страницу без сохранения?",
        "unsaved_changes_line2": "Все ваши несохраненные изменения будут потеряны",
        "use_ssl": "Используйте зашифрованное соединение (SSL) при доступе к этому серверу",
        "set_reply_to_field": "Установить поле «Ответить» письма:",
        "save_and_leave": "Сохранить и выйти",
        "save_delegate_folder": "Сохранять копии отправленных сообщений в делегированной папке «Отправленные»",
        "use_persona": "Использовать этот алиас",
        "use_personas_line1": "Используйте алиасы для быстрого изменения многих настроек при отправке писем.",
        "use_personas_line2": "Например, если вы иногда отправляете электронные письма в определенной роли на работе, создайте для этого алиас.",
        "when_composing": "При создании, ответе или пересылке сообщения в папке (папках):",
        "when_replying": "При ответе или пересылке сообщений, отправленных по адресу:",
        "button": "Кнопка",
        "click_to_copy": "Нажмите чтобы скопировать",
        "details_feedback__collected_msg": "Следующая информация будет отправлена вместе с сообщением для обратной связи",
        "allow_all_permission_to_send_feedback_to_zextras": "Разрешить всем настройкам из раздела \"Конфиденциальность\" отправлять сообщения для обратной связи",
        "detailsfeedback__collected_msg": "Следующая информация будет отправлена вместе с сообщением обратной связи",
        "allow_permission_to_send_feedback_to_zextras": "Следующая информация будет отправлена вместе с сообщением обратной связи",
        "allow_permission_to_send_data_to_zextras": "Разрешить настройке из раздела \"Конфиденциальность\" отправлять полные данные об ошибках в Zextras",
        "post_feedback_send_helper_text_line_3": "Помогите нам стать лучше!",
        "feedback_request_data": "Запросить данные для обратной связи:",
        "total_servers": "Общее количество серверов",
        "total_domains": "Общее количество доменов",
        "total_accounts": "Общее количество учетных записей",
        "thank_you_for_feedback": "Спасибо за отзыв!",
        "post_feedback_send_helper_text_line_2": "Чтобы улучшить Carbonio, мы проводим непрерывные сеансы тестирования,",
        "feedback_helper_text": "Хотите принять участие?",
        "enable_all_permission_to_send_feedback_to_zextras": "Включите все следующие разрешения из раздела конфиденциальности, чтобы отправить отзыв",
        "enable_all__following_permission_to_send_feedback_to_zextras": "Включите все следующие разрешения в разделе конфиденциальности, чтобы отправить отзыв",
        "carbonio_community_edition": "Carbonio Community Edition",
        "carbonio_admin_ui_version": "Версия Carbonio AdminUI",
        "carbonio_backend_version": "Backend Version Carbonio"
    },
    "board": {
        "close_tab": "Закрыть вкладку",
        "close_tabs": "Закройте все свои вкладки",
        "enlarge": "Увеличить окно",
        "hide": "Спрятать окно",
        "reduce": "Уменьшить окно",
        "show_tabs": "Показать другие вкладки"
    },
    "locale": {
        "label_chinese": "Китайский-{{value}}",
        "label_japanese": "Японский-{{value}}",
        "label_thai": "Тайский-{{value}}",
        "spanish": "Испанский",
        "English": "Английский",
        "chinese_china": "Китайский",
        "german": "Немецкий",
        "hindi": "Хинди",
        "italian": "Итальянский",
        "japanese": "Японский",
        "dutch": "Голландский",
        "label_dutch": "Голландский-{{value}}",
        "label_english": "Английский-{{value}}",
        "label_german": "Немецкий-{{value}}",
        "label_hindi": "Хинди-{{value}}",
        "label_italian": "Итальянский-{{value}}",
        "label_portuguese": "Португальский-{{value}}",
        "label_portuguese_brazil": "Португальский-{{value}}",
        "label_romanian": "Румынский-{{value}}",
        "label_russian": "Русский - {{value}}",
        "label_spanish": "Испанский-{{value}}",
        "label_turkish": "Турецкий-{{value}}",
        "portuguese": "Португальский",
        "portuguese_brazil": "Португальский ( Бразильский)",
        "romanian": "Румынский",
        "russian": "Русский",
        "thai": "Тайский",
        "turkish": "Турецкий",
        "french": "Французский",
        "label_french": "Французский - {{value}}",
        "vietnamese": "Вьетнамский",
        "polish": "Польский"
    },
    "timezone": {
        "minsk": "{{value}} Минск",
        "africa_algiers": "{{value}} Западная Центральная Африка",
        "africa_cairo": "{{value}} Египет",
        "africa_harare": "{{value}} Хараре, Претория",
        "africa_juba": "{{value}} Джуба",
        "africa_khartoum": "{{value}} Хартум",
        "africa_monrovia": "{{value}} Монровия",
        "africa_nairobi": "{{value}} Найроби",
        "africa_sao_tome": "{{value}} Сан-Томе",
        "africa_tripoli": "{{value}} Триполи",
        "africa_windhoek": "{{value}} Намибия",
        "america_adak": "{{value}} Адак",
        "america_anchorage": "{{value}} Аляска",
        "america_araguaina": "{{value}} Арагуайна",
        "america_argentina_buenos_aires": "{{value}} Аргентина",
        "america_asuncion": "{{value}} Асунсьон",
        "america_bahia": "{{value}} Сальвадор",
        "america_bogota": "{{value}} Колумбия",
        "america_cancun": "{{value}} Канкун, Четумаль",
        "america_caracas": "{{value}} Каракас",
        "america_cayenne": "{{value}} Кайенна, Форталеза",
        "america_chicago": "{{value}} США/ Центральная Канада",
        "america_chihuahua": "{{value}} Чиуауа, Ла-Пас, Масатлан",
        "america_cuiaba": "{{value}} Куяба",
        "america_denver": "{{value}} US/Canada Mountain",
        "america_fort_nelson": "{{value}} Форт Нельсон",
        "america_grand_turk": "{{value}} Острова Теркс и Кайкос",
        "america_guatemala": "{{value}} Центральная Америка",
        "america_halifax": "{{value}} Атлантическое время (Канада)",
        "america_havana": "{{value}} Гавана",
        "america_indiana_indianapolis": "{{value}} Индиана (Восток)",
        "america_los_angeles": "{{value}} США/Канада, Тихоокеанский регион",
        "america_miquelon": "{{value}} Микелон",
        "america_montevideo": "{{value}} Монтевидео",
        "america_new_york": "{{value}} Восточная часть США/Канады",
        "america_phoenix": "{{value}} Аризона",
        "america_port-au-prince": "{{value}} Порт-о-Пренс",
        "america_punta_arenas": "{{value}} Пунта_Аренас",
        "america_regina": "{{value}} Саскачеван",
        "america_sao_paulo": "{{value}} Бразилия",
        "america_st_johns": "{{value}} Ньюфаундленд",
        "america_tijuana": "{{value}} Нижняя Калифорния",
        "america_whitehorse": "{{value}}Yukon",
        "asia_almaty": "{{value}} Астана",
        "asia_amman": "{{value}} Иордания",
        "asia_baghdad": "{{value}} Ирак",
        "asia_baku": "{{value}} Баку",
        "asia_barnaul": "{{value}} Барнаул",
        "asia_beirut": "{{value}} Бейрут",
        "asia_chita": "{{value}} Чита",
        "asia_colombo": "{{value}} Шри Джаяварденепура Котте",
        "asia_damascus": "{{value}} Дамаск",
        "asia_dhaka": "{{value}} Дакка",
        "asia_gaza": "{{value}} Газа",
        "asia_hong_kong": "{{value}} Пекин, Чунцин, Гонконг, Уру М Фаза",
        "asia_hovd": "{{value}} Ховд",
        "asia_irkutsk": "{{value}} Иркутск (RTZ 7)",
        "asia_jerusalem": "{{value}} Иерусалим",
        "asia_kabul": "{{value}} Кабул",
        "asia_kamchatka": "{{value}} Анадырь, Петропавловск-Камчатский (RTZ 11)",
        "asia_karachi": "{{value}} Исламабад, Карачи",
        "asia_kathmandu": "{{value}} Катманду",
        "asia_krasnoyarsk": "{{value}} Красноярск (RTZ 6)",
        "asia_kuala_lumpur": "{{value}} Куала Лумпур",
        "asia_kuwait": "{{value}} Кувейт, Эр-Рияд",
        "asia_magadan": "{{value}} Магадан",
        "asia_muscat": "{{value}} Абу-Даби, Маскат",
        "asia_novosibirsk": "{{value}} Новосибирск (RTZ 5)",
        "asia_omsk": "{{value}} Омск",
        "asia_pyongyang": "{{value}} Пхеньян",
        "asia_qyzylorda": "{{value}} Кызылорда",
        "asia_sakhalin": "{{value}} Сахалин",
        "asia_seoul": "{{value}} Корея",
        "asia_singapore": "{{value}} Сингапур",
        "asia_srednekolymsk": "{{value}} Чокурдах (RTZ 10)",
        "asia_taipei": "{{value}} Taipei",
        "asia_tashkent": "{{value}} Ташкент",
        "asia_tehran": "{{value}} Тегеран",
        "asia_tokyo": "{{value}} Япония",
        "asia_tomsk": "{{value}} Томск",
        "asia_ulaanbaatar": "{{value}}Ulaanbaatar",
        "asia_yakutsk": "{{value}} Якурск (RTZ 8)",
        "asia_yerevan": "{{value}} Ереван",
        "africa_casablanca": "{{value}} Касабланка",
        "america_guyana": "{{value}} Джорджтаун, Ла-Пас, Манаус, Сан-Хуан",
        "america_mexico_city": "{{value}} Гвадалахара, Мехико, Монтеррей",
        "america_santiago": "{{value}} Тихоокеанский регион Южная Америка",
        "asia_bangkok": "{{value}} Бангкок, Ханой, Джакарта",
        "asia_kolkata": "{{value}} Ченнаи, Калькутта, Мумбаи, Нью-Дели",
        "asia_tbilisi": "{{value}} Тбилиси",
        "asia_vladivostok": "{{value}} Владивосток, Магадан (RTZ 9)",
        "asia_yangon": "{{value}} Янгон",
        "asia_yekaterinburg": "{{value}} Екатеринбург (RTZ 4)",
        "atlantic_azores": "{{value}} Азорские острова",
        "atlantic_south_georgia": "{{value}} Средняя Атлантика",
        "australia_adelaide": "{{value}} Аделаида",
        "australia_darwin": "{{value}} Дарвин",
        "australia_eucla": "{{value}} Евкла",
        "australia_hobart": "{{value}} Хобарт",
        "australia_lord_howe": "{{value}} Лорд_Хау",
        "australia_perth": "{{value}} Перт",
        "etc_gmt+12": "{{value}}Dateline",
        "europe_astrakhan": "{{value}} Астрахань",
        "atlantic_cape_verde": "{{value}} Острова Кабо-Верде.",
        "europe_athens": "{{value}} Афины, Бейрут, Бухарест, Стамбул",
        "europe_belgrade": "{{value}} Белград, Братислава, Будапешт, Любляна, Прага",
        "europe_brussels": "{{value}} Брюссель, Копенгаген, Мадрид, Париж",
        "europe_bucharest": "{{value}} Бухарест",
        "europe_chisinau": "{{value}} Кишинев",
        "europe_helsinki": "{{value}} Хельсинки, Киев, Рига, София, Таллинн, Вильнюс",
        "europe_istanbul": "{{value}} Стамбул",
        "europe_london": "{{value}} Великобритания, Ирландия, Португалия",
        "europe_minsk": "{{value}} Минск",
        "europe_moscow": "{{value}} Москва, Санкт-Петербург, Волгоград (RTZ 2)",
        "europe_saratov": "{{value}} Саратов",
        "europe_volgograd": "{{value}} Волгоград",
        "europe_warsaw": "{{value}} Сараево, Скопье, Варшава, Загреб",
        "indian_mauritius": "{{value}} Порт-Луи",
        "pacific_apia": "{{value}} Самоа",
        "pacific_bougainville": "{{value}} Стандартное время Бугенвиля",
        "pacific_easter": "{{value}} Остров Пасхи",
        "pacific_fiji": "{{value}} Фиджи",
        "pacific_honolulu": "{{value}} Гавайи",
        "pacific_kiritimati": "{{value}} Остров Киритимати",
        "pacific_marquesas": "{{value}} Маркизские острова",
        "pacific_midway": "{{value}} Самоа",
        "pacific_norfolk": "{{value}} Самоа",
        "australia_brisbane": "{{value}} Брисбен",
        "australia_sydney": "{{value}} Канберра, Мельбурн, Сидней",
        "europe_berlin": "{{value}} Амстердам, Берлин, Берн, Рим, Стокгольм, Вена",
        "europe_kaliningrad": "{{value}} Калининград (RTZ 1)",
        "europe_samara": "{{value}} Ижевск, Самара (RTZ 3)",
        "pacific_auckland": "{{value}} Новая Зеландия",
        "pacific_chatham": "{{value}} Чатем",
        "pacific_guadalcanal": "{{value}} Соломоновы острова. / Новая Каледония",
        "pacific_guam": "{{value}} Гуам, Порт-Морсби",
        "pacific_tongatapu": "{{value}} Нукуалофа",
        "utc": "{{value}} Всемирное координированное время",
        "abu_dhabi_muscat": "{{value}} Абу-Даби, Маскат",
        "alaska": "{{value}} Аляска",
        "amsterdam_berlin_bern_rome_stockholm_vienna": "{{value}} Амстердам, Берлин, Берн, Рим, Стокгольм, Вена",
        "anadyr_petropavlovsk_kamchatsky_rtz11": "{{value}} Анадырь, Петропавловск-Камчатский (RTZ 11)",
        "asuncion": "{{value}} Асунсьон",
        "athens_beirut_bucharest_istanbul": "{{value}} Афины, Бейрут, Бухарест, Стамбул",
        "beijing_chongqing_hong_kong_urumqi": "{{value}} Пекин, Чунцин, Гонконг, Урумиай",
        "brussels_copenhagen_madrid_paris ": "{{value}} Брюссель, Копенгаген, Мадрид, Париж ",
        "chennai_kolkata_mumbai_new_delhi": "{{value}} Ченнаи, Калькутта, Мумбаи, Нью-Дели",
        "coordinated_universal_time": "{{value}} Всемирное координированное время",
        "ekaterinburg_rtz_4": "{{value}} Екатеринбург (RTZ 4)",
        "georgetown_la_paz_manaus_san_juan": "{{value}} Джорджтаун, Ла-Пас, Манаус, Сан-Хуан",
        "argentina": "{{value}} Аргентина",
        "arizona": "{{value}} Аризона",
        "atlantic_time_canada": "{{value}} Атлантическое время (Канада)",
        "azores": "{{value}} Азорские острова",
        "baja_california": "{{value}} Нижняя Калифорния",
        "baku": "{{value}} Баку",
        "bangkok_hanoi_jakarta": "{{value}} Бангкок, Ханой, Джакарта",
        "beirut": "{{value}} Бейрут",
        "belgrade_bratislava_budapest_ljubljana_prague": "{{value}} Белград, Братислава, Будапешт, Любляна, Прага",
        "brasilia": "{{value}} Бразилия",
        "britain_ireland_portugal": "{{value}} Великобритания, Ирландия, Португалия",
        "cape_verde_is": "{{value}}Острова Кабо-Верде.",
        "caracas": "{{value}} Каракас",
        "casablanca": "{{value}} Касабланка",
        "cayenne_fortaleza": "{{value}} Кайенна, Фортелеза",
        "central_america": "{{value}} Центральная Америка",
        "chihuahua_la_paz_mazatlan": "{{value}} Чиуауа, Ла-Пас, Масатлан",
        "chita": "{{value}} Чита",
        "christmas_island": "{{value}} Остров Рождества",
        "colombia": "{{value}} Колумбия",
        "cuiaba": "{{value}} Куяба",
        "damascus": "{{value}} Дамаск",
        "darwin": "{{value}} Дарвин",
        "dhaka": "{{value}} Дакка",
        "egypt": "{{value}} Египет",
        "eucla": "{{value}} Евкла",
        "gmt_02": "{{value}} GMT-02",
        "gmt_11": "{{value}} GMT-11",
        "magadan": "{{value}} Магадан",
        "sarajevo_skopje_warsaw_zagreb": "{{value}} Сараево, Скопье, Варшава, Загреб",
        "mid_atlantic": "{{value}} Средняя Атлантика",
        "us_canada_eastern": "{{value}} США/Восточная Канада",
        "kaliningrad_rtz_1": "{{value}} Калининград (RTZ 1)",
        "moscow_st_petersburg_volgograd_rtz_2": "{{value}} Москва, Санкт-Петербург, Волгоград (RTZ 2)",
        "west_central_africa": "{{value}} Западно-Центральная Африка",
        "dateline": "{{value}} Меридиан",
        "greenland": "{{value}}Гренландия",
        "guadalajara_mexico_city_monterrey ": "{{value}} Гвадалахара, Мехико, Монтеррей ",
        "hawaii": "{{value}} Гавайи",
        "helsinki_kyiv_riga_sofia_tallinn_vilnius": "{{value}} Хельсинки, Киев, Рига, София, Таллинн, Вильнюс",
        "indiana_east": "{{value}} Индиана (Восток)",
        "iraq": "{{value}} Ирак",
        "irkutsk_rtz_7": "{{value}} Иркутск (RTZ 7)",
        "istanbul": "{{value}}⁣ Стамбул",
        "jerusalem": "{{value}} Иерусалим",
        "jordan": "{{value}} Иордания",
        "kabul": "{{value}} Кабул",
        "kathmandu": "{{value}} Катманду",
        "korea": "{{value}} Корея",
        "krasnoyarsk_rtz_6": "{{value}} Красноярск (RTZ 6)",
        "kuwait_riyadh": "{{value}} Кувейт, Эр-Рияд",
        "la_paz": "{{value}} Ла-Пас",
        "harare_pretoria": "{{value}} Harare, Pretoria",
        "manaus": "{{value}} Манаус",
        "monrovia": "{{value}} Монровия",
        "montevideo": "{{value}} Монтевидео",
        "nairobi": "{{value}} Найроби",
        "namibia": "{{value}} Намибия",
        "newfoundland": "{{value}} Ньюфаундленд",
        "nuku_alofa": "{{value}} Нукуалофа",
        "pacific_south_america": "{{value}} Тихий океан Южная Америка",
        "port_louis": "{{value}} Порт-Луи",
        "pyongyang": "{{value}} Пхеньян",
        "samoa": "{{value}} Самоа",
        "saskatchewan": "{{value}} Саскачеван",
        "sri_jayawardenepura_kotte": "{{value}} Шри Джаяварденепура Котте",
        "tbilisi": "{{value}} Тбилиси",
        "tehran": "{{value}} Тегеран",
        "us_canada_central": "{{value}} США/Центральная Канада",
        "us_canada_pacific": "{{value}} США/Канада Тихий океан",
        "vladivostok_magadan": "{{value}} владивосток_магадан_rtz_9",
        "yangon": "{{value}} Янгон",
        "yerevan": "{{value}} Ереван",
        "us_canada_mountain": "{{value}} США/Канада"
    },
    "feedback": {
        "behaviors": "Поведение",
        "report_something": "Вы хотите что-то сообщить?",
        "select_a_module": "Выбрать модуль",
        "select_a_topic": "Выбрать тему",
        "send": "ОТПРАВИТЬ",
        "success": "Спасибо за отзыв",
        "user_interface": "Пользовательский интерфейс",
        "write_here": "Напишите ваш отзыв здесь",
        "error": "При отправке отзыва произошла ошибка",
        "missing_features": "Отсутствующие функции",
        "explanation": "Оставьте Ваш отзыв о работе Zextras Server. Ваше мнение важно для нас, чтобы улучшить наш продукт.",
        "other": "Другое",
        "hint": "Внимание: Указывайте тему при помощи списка модулей перед написанием отзыва. Спасибо за вашу помощь.",
        "write_here_placeholder_text": "Привет! Начните писать здесь свои отзывы :)\n\n\nЭто будет отправлено анонимно, поэтому поделитесь вашим мнением о продукте",
        "send_feedback": "ПОДЕЛИТЕСЬ ВАШИМ ОТЗЫВОМ С НАМИ",
        "goto_privacy": "Перейти к параметрам конфиденциальности",
        "count_user_in_helper_button_text": "Да, я буду принимать участие в опросах!",
        "enable_feedback": "Включить обратную связь",
        "enable_privacy_setting": "Включите настройку конфиденциальности, чтобы отправить отзыв"
    },
    "passwords_recovery_settings": {
        "title": "Настройки учетной записи для восстановления пароля"
    },
    "primary_account": {
        "title": "Настройки основной учетной записи"
    },
    "messages": {
        "permanent_delete_title": "Вы уверены, что хотите навсегда удалить этот элемент?",
        "permanent_delete_body": "Если вы навсегда удалите этот Алиас, вы не сможете ее восстановить. Продолжать?"
    },
    "share": {
        "is_contained_in": "Содержится в"
    },
    "labels": {
        "help_center": "Справочный центр"
    },
    "create": "Создать",
    "privacy": {
        "send_full_error_data_to_zextras": "Отправить полные данные об ошибках в Zextras",
        "allow_live_survey_feedbacks": "Разрешить опросы в реальном времени",
        "allow_data_analytics": "Разрешить аналитику данных"
    }
}
